[
  {
    "DDLastDel": 3638,
    "Next": 3868,
    "LastDel": "04/26/19",
    "JulianDelivery": "04/18/20",
    "LastCharge": "05/16/18",
    "LastFullFill": "01/20/19"
  },
  {
    "DDLastDel": 8654,
    "Next": 3785,
    "LastDel": "02/20/15",
    "JulianDelivery": "04/18/20",
    "LastCharge": "07/16/18",
    "LastFullFill": "01/20/19"
  },
  {
    "DDLastDel": 6422,
    "Next": 1148,
    "LastDel": "04/14/19",
    "JulianDelivery": "04/18/20",
    "LastCharge": "05/17/18",
    "LastFullFill": "01/20/12"
  }
]
