[
    {
    "Type": "H",
    "Description": "HEATING/FURNACE",
    "Make": "HH GREG",
    "Model": "funrace45yg",
    "BTU Rating": 0,
    "SerialNumber": "S5F-7FG78JKO543D-GFJH0",
    "Purchase Date": "00/00/00",
    "Begin Service Contract": "00/00/00",
    "Tied To Tank": " ",
    "Sold By": "Ryan Mahon",
    "Service Contract Type": 2,
    "End Service Contract": "00/00/00",
    "Scheduled Service Month": 0,
    "Comments": "N/A"

  },
  {
    "Type": "R",
    "Description": "RANGE/COOKSTOVE",
    "Make": "trane",
    "Model": "e32rewp8dpox",
    "BTU Rating": 0,
    "SerialNumber": "D4G3-DEKWJFBVS-21332R"
  },
  {
    "Type": "W",
    "Description": "TRADITIONAL WATER HEATER",
    "Make": "Frys",
    "Model": "French Fry",
    "BTU Rating": 0,
    "SerialNumber": "3EDJ-32IOCNI-DKKW4"
  },
  {
    "Type": "W",
    "Description": "TRADITIONAL WATER HEATER",
    "Make": "Frys",
    "Model": "French Fry",
    "BTU Rating": 0,
    "SerialNumber": "32R3-WAFCED23C21-1E2DA"
  }
  ]
