[
  {
    "name": "01/18-12/18",
    "Jan": 18.9,
    "Feb": 28.8,
    "Mar": 39.3,
    "Apr": 81.4,
    "May": 47,
    "Jun": 20.3,
    "Jul": 24,
    "Aug": 35.6,
    "Sep": 60,
    "Oct": 73,
    "Nov": 84,
    "Dec": 96,
    "TankRRN": 123456
  },
  {
    "name": "01/19-12/19",
    "Jan": 12.4,
    "Feb": 23.2,
    "Mar": 34.5,
    "Apr": 99.7,
    "May": 52.6,
    "Jun": 35.5,
    "Jul": 37.4,
    "Aug": 42.4,
    "Sep": 60,
    "Oct": 73,
    "Nov": 84,
    "Dec": 96,
    "TankRRN": 123456
  },
  {
    "name": "01/17-12/17",
    "Jan": 60,
    "Feb": 53,
    "Mar": 47,
    "Apr": 42,
    "May": 40,
    "Jun": 45,
    "Jul": 48,
    "Aug": 52,
    "Sep": 60,
    "Oct": 64,
    "Nov": 71,
    "Dec": 81,
    "TankRRN": 123456
  },
  {
    "name": "01/18-12/18",
    "Jan": 21.3,
    "Feb": 29.9,
    "Mar": 33.9,
    "Apr": 84.1,
    "May": 49,
    "Jun": 23,
    "Jul": 26,
    "Aug": 36.5,
    "Sep": 64,
    "Oct": 78,
    "Nov": 81,
    "Dec": 92,
    "TankRRN": 123457
  },
  {
    "name": "01/19-12/19",
    "Jan": 14.2,
    "Feb": 22.3,
    "Mar": 35.4,
    "Apr": 97.9,
    "May": 56.2,
    "Jun": 37,
    "Jul": 34.7,
    "Aug": 44.2,
    "Sep": 64,
    "Oct": 72,
    "Nov": 81,
    "Dec": 98,
    "TankRRN": 123457
  },
  {
    "name": "01/17-12/17",
    "Jan": 61,
    "Feb": 57,
    "Mar": 42,
    "Apr": 47,
    "May": 38,
    "Jun": 41,
    "Jul": 51,
    "Aug": 56,
    "Sep": 68,
    "Oct": 69,
    "Nov": 77,
    "Dec": 80,
    "TankRRN": 123457
  },
  {
    "name": "01/18-12/18",
    "Jan": 25.2,
    "Feb": 28.3,
    "Mar": 36.1,
    "Apr": 86.2,
    "May": 49,
    "Jun": 23,
    "Jul": 26,
    "Aug": 36.5,
    "Sep": 64,
    "Oct": 78,
    "Nov": 81,
    "Dec": 92,
    "TankRRN": 123458
  },
  {
    "name": "01/19-12/19",
    "Jan": 16.2,
    "Feb": 21.3,
    "Mar": 37.4,
    "Apr": 94.9,
    "May": 56.2,
    "Jun": 37,
    "Jul": 34.7,
    "Aug": 44.2,
    "Sep": 64,
    "Oct": 72,
    "Nov": 81,
    "Dec": 98,
    "TankRRN": 123458
  },
  {
    "name": "01/17-12/17",
    "Jan": 68,
    "Feb": 52,
    "Mar": 44,
    "Apr": 49,
    "May": 38,
    "Jun": 41,
    "Jul": 51,
    "Aug": 56,
    "Sep": 68,
    "Oct": 69,
    "Nov": 77,
    "Dec": 80,
    "TankRRN": 123458
  }
]
